movoid_xml_data/__init__.py
movoid_xml_data/label_data.py
movoid_xml_data/tag_data.py
movoid_xml_data-1.1.1.dist-info/METADATA
movoid_xml_data-1.1.1.dist-info/WHEEL
movoid_xml_data-1.1.1.dist-info/top_level.txt
movoid_xml_data-1.1.1.dist-info/RECORD
