Metadata-Version: 2.1
Name: movoid_xml_data
Version: 1.1.1
Home-page: 
Author: movoid
Author-email: bobrobotsun@163.com
Requires-Dist: lxml
Requires-Dist: cssselect
